package_name_checker/__init__.py
package_name_checker/app.py
package_name_checker-1.0.0.dist-info/LICENSE
package_name_checker-1.0.0.dist-info/METADATA
package_name_checker-1.0.0.dist-info/WHEEL
package_name_checker-1.0.0.dist-info/entry_points.txt
package_name_checker-1.0.0.dist-info/top_level.txt
package_name_checker-1.0.0.dist-info/RECORD
